Metadata-Version: 2.1
Name: facenet-pytorch-custom
Version: 2.5.2.dev2
Summary: Pretrained Pytorch face detection and recognition models original - https://github.com/timesler/facenet-pytorch
Home-page: https://github.com/ShivamSinghal1/facenet-pytorch
Author: Shivam Singhal
Author-email: shivamsinghal1012@gmail.com
Classifier: Programming Language :: Python :: 3
Classifier: License :: OSI Approved :: MIT License
Classifier: Operating System :: OS Independent
License-File: LICENSE.md
Requires-Dist: numpy <2.0.0,>=1.24.0
Requires-Dist: Pillow <10.3.0,>=10.2.0
Requires-Dist: requests <3.0.0,>=2.0.0
Requires-Dist: torch <=2.4.0,>=2.2.0
Requires-Dist: torchvision <=0.19.0,>=0.17.0
Requires-Dist: tqdm <5.0.0,>=4.0.0
